derm_tiff/__init__.py
derm_tiff/derm_tiff_image.py
derm_tiff/io.py
derm_tiff-2.1.2.dist-info/METADATA
derm_tiff-2.1.2.dist-info/WHEEL
derm_tiff-2.1.2.dist-info/RECORD
