Metadata-Version: 2.1
Name: derm-tiff
Version: 2.1.2
Summary: Utilities for tiff images created by DermAnnotation
Author: kawa-yo
Author-email: yoshito.kawasaki.pub@gmail.com
Requires-Python: >=3.8,<4.0
Classifier: Programming Language :: Python :: 3
Classifier: Programming Language :: Python :: 3.8
Classifier: Programming Language :: Python :: 3.9
Classifier: Programming Language :: Python :: 3.10
Classifier: Programming Language :: Python :: 3.11
Requires-Dist: Pillow (>=9.4.0,<10.0.0)
Requires-Dist: nptyping (>=2.2.0,<3.0.0)
Requires-Dist: numpy (>=1.24.2,<2.0.0)
